accelerated_scan/__init__.py
accelerated_scan/complex.py
accelerated_scan/ref.py
accelerated_scan/scalar.py
accelerated_scan/warp.cuh
accelerated_scan/warp.py
accelerated_scan-0.3.1.dist-info/METADATA
accelerated_scan-0.3.1.dist-info/WHEEL
accelerated_scan-0.3.1.dist-info/licenses/LICENSE
accelerated_scan-0.3.1.dist-info/RECORD
