Metadata-Version: 2.4
Name: accelerated-scan
Version: 0.3.1
Author-email: Volodymyr Kyrylov <vol@wilab.org.ua>
License: MIT License
License-File: LICENSE
Classifier: License :: OSI Approved :: MIT License
Classifier: Operating System :: OS Independent
Classifier: Programming Language :: Python :: 3
Requires-Python: >=3.10
Requires-Dist: torch>=2.9.0
